Gringotts-0.1.0.dist-info/METADATA
Gringotts-0.1.0.dist-info/RECORD
Gringotts-0.1.0.dist-info/WHEEL
Gringotts-0.1.0.dist-info/top_level.txt
gringotts/__init__.py
