Metadata-Version: 2.1
Name: Gringotts
Version: 0.1.0
Summary: Tools for personal financial planning
Home-page: https://pypi.org/project/gringotts/
Author: J. Chamness
Author-email: jchamness@gmail.com
License: UNKNOWN
Platform: UNKNOWN
Classifier: Programming Language :: Python :: 3
Classifier: License :: OSI Approved :: GNU General Public License v3 (GPLv3)
Classifier: Operating System :: OS Independent
